MANIFEST.in
setup.py
pycricket/__init__.py
pycricket/cricket.py
pycricket/matches.csv
pycricket.egg-info/PKG-INFO
pycricket.egg-info/SOURCES.txt
pycricket.egg-info/dependency_links.txt
pycricket.egg-info/requires.txt
pycricket.egg-info/top_level.txt
pycricket/data/1/1000851.xml
pycricket/data/1/1000853.xml
pycricket/data/1/1000855.xml
pycricket/data/1/1000881.xml
pycricket/data/1/1000883.xml
pycricket/data/1/1000885.xml
pycricket/data/1/1000887.xml
pycricket/data/1/1000889.xml
pycricket/data/1/1000891.xml
pycricket/data/1/1000893.xml
pycricket/data/1/1000895.xml
pycricket/data/1/1001349.xml
pycricket/data/1/1001371.xml
pycricket/data/1/1001373.xml
pycricket/data/1/1001375.xml
pycricket/data/1/1003271.xml
pycricket/data/1/1003273.xml
pycricket/data/1/1004251.xml
pycricket/data/1/1004253.xml
pycricket/data/1/1004255.xml
pycricket/data/1/1004261.xml
pycricket/data/1/1004269.xml
pycricket/data/1/1004277.xml
pycricket/data/1/1004283.xml
pycricket/data/1/1004285.xml
pycricket/data/1/1004729.xml
pycricket/data/1/1007649.xml
pycricket/data/1/1007651.xml
pycricket/data/1/1007653.xml
pycricket/data/1/1007655.xml
pycricket/data/1/1007657.xml
pycricket/data/1/1007659.xml
pycricket/data/1/1014845.xml
pycricket/data/1/1014847.xml
pycricket/data/1/1019973.xml
pycricket/data/1/1019975.xml
pycricket/data/1/1019977.xml
pycricket/data/1/1019979.xml
pycricket/data/1/1019981.xml
pycricket/data/1/1019983.xml
pycricket/data/1/1019985.xml
pycricket/data/1/1019987.xml
pycricket/data/1/1019993.xml
pycricket/data/1/1019995.xml
pycricket/data/1/1020013.xml
pycricket/data/1/1020017.xml
pycricket/data/1/1020029.xml
pycricket/data/1/1022593.xml
pycricket/data/1/1022595.xml
pycricket/data/1/1022597.xml
pycricket/data/1/1022599.xml
pycricket/data/1/1024041.xml
pycricket/data/1/1024043.xml
pycricket/data/1/1026847.xml
pycricket/data/1/1026849.xml
pycricket/data/1/1026851.xml
pycricket/data/1/1029819.xml
pycricket/data/1/1029821.xml
pycricket/data/1/1029823.xml
pycricket/data/1/1029825.xml
pycricket/data/1/1029827.xml
pycricket/data/1/1030213.xml
pycricket/data/1/1030215.xml
pycricket/data/1/1030217.xml
pycricket/data/1/1030219.xml
pycricket/data/1/1030221.xml
