Metadata-Version: 1.1
Name: pycricket
Version: 0.9
Summary: A library for fetching cricket scorecards of past cricket matches
Home-page: https://github.com/codophobia/cricket-scorecards-and-commentary-with-python
Author: Shivam Mitra
Author-email: shivamm389@gmail.com
License: GPLv2
Download-URL: https://github.com/codophobia/cricket-scorecards-and-commentary-with-python/tarball/0.2
Keywords: cricket,scorecards
Platform: UNKNOWN
